<screen name="ScreenMain" position="fill" flags="wfNoBorder" backgroundColor="transparent">
    <panel name="Screen_Window_Full_Backdrop" />
    <panel position="20,20" size="e-40,e">
        <widget font="Bold;28" name="searchinfo" position="5,65" size="e,40" transparent="1"/>
        <widget name="cover" position="e-485,115" scale="1" size="480,720" cornerRadius="10"/>
        <widget source="list" render="Listbox" position="5,115" scrollbarMode="showOnDemand" size="e-505,800"
                font="Regular;24" itemHeight="40" itemCornerRadius="6" transparent="1">
            <convert type="StringList" />
        </widget>
        <ePixmap pixmap="/usr/lib/enigma2/python/Plugins/Extensions/TMDBCockpit/skin/images/tmdb.png" position="e-485+65,880" size="350,30" scale="1" alphatest="blend"/>
    </panel>
</screen>